Metadata-Version: 1.1
Name: stream-cli
Version: 1.0.0
Summary: 
